{
  "image": {
    "type": "image",
    "texture": "textures/ui/xboxconversionkeyart",
    "size": [ "100% - 2px", "40%" ]
  },

  "dialog_content": {
    "type": "stack_panel",
    "size": [ "100% - 4px", "100% - 20px" ],
    "offset": [ 0, "20px" ],
    "controls": [
      {
        "image_panel@convert_purchases_to_xbl.image": {}
      },
      {
        "padding_0@convert_purchases_to_xbl.padding": {}
      },
      {
        "description_label_wrapper@common.tts_label_focus_wrapper": {
          "size": [ "100%", "fill" ],
          "$tts_label_panel": "convert_purchases_to_xbl.scrolling_panel",
          "$focus_border_size": [ "100% + 2px", "100%" ]
        }
      },
      {
        "padding_1@convert_purchases_to_xbl.padding": {}
      },
      {
        "button_panel": {
          "type": "stack_panel",
          "orientation": "horizontal",
          "size": [ "100%", 20 ],
          "controls": [
            {
              "save_to_xbox_button@common_buttons.light_text_button": {
                "$pressed_button_name": "button.save_to_xbl",
                "$button_text": "xbl.savePurchase.saveButton",
                "size": [ "50% - 1px", 20 ],
                "$button_text_max_size": [ "100%", 20 ],
                "$button_focus_precedence": 10
              }
            },
            {
              "padding": {
                "type": "panel",
                "size": [ 2, "100%" ]
              }
            },
            {
              "leave_on_device_button@common_buttons.light_text_button": {
                "$pressed_button_name": "button.leave_on_device",
                "$button_text": "xbl.savePurchase.leaveOnDevice",
                "size": [ "50% - 1px", 20 ],
                "$button_text_max_size": [ "100%", 20 ]
              }
            }
          ]
        }
      },
      {
        "padding_2": {
          "type": "panel",
          "size": [ 0, 15 ]
        }
      }
    ]
  },
  
  "convert_purchases_to_xbl_screen": {
    "button_mappings": [
      {
        "from_button_id": "button.menu_cancel",
        "to_button_id": "button.leave_on_device",
        "mapping_type": "global"
      }
    ],
    // 空的顶部面板 - 填充安全角
    "$header_safezone_control": "cube_ui_common.empty_headbar",// 顶部
    "$header_bar_control": "cube_ui_common.empty_headbar",// 侧边
    
    "$screen_bg_content": "cube_ui_background.screen_blur_background_content",
    "$screen_content": "convert_purchases_to_xbl.convert_purchases_to_xbl_screen_content"
  },

  "convert_purchases_to_xbl_screen_content": {
    "type": "panel",
    "controls": [
      {
        "headbar@cube_ui_common.headbar": {
          "$title": "xbl.savePurchase.title",
          "$back_button_ignored": true,
          "layer": 1
        }
      },
      { "panel@convert_purchases_to_xbl.dialog_content": { "layer": 1 } }
    ]
  }
}